ag_llama2_hub_s/__init__.py
ag_llama2_hub_s/__main__.py
ag_llama2_hub_s/model.py
ag_llama2_hub_s-0.0.21.data/scripts/download.py
ag_llama2_hub_s-0.0.21.data/scripts/render.py
ag_llama_hub/__init__.py
ag_llama_hub/__main__.py
ag_llama_hub/choice.py
ag_llama_hub/model.py
ag_llama_hub/tokenizer.py
ag_llama_hub_s/__init__.py
ag_llama_hub_s/__main__.py
ag_llama_hub_s/model.py
ag_llama2_hub_s-0.0.21.dist-info/METADATA
ag_llama2_hub_s-0.0.21.dist-info/WHEEL
ag_llama2_hub_s-0.0.21.dist-info/top_level.txt
ag_llama2_hub_s-0.0.21.dist-info/RECORD
